adk_agui_middleware/__init__.py
adk_agui_middleware/endpoint.py
adk_agui_middleware/py.typed
adk_agui_middleware/sse_service.py
adk_agui_middleware/base_abc/__init__.py
adk_agui_middleware/base_abc/sse_service.py
adk_agui_middleware/config/__init__.py
adk_agui_middleware/config/log.py
adk_agui_middleware/data_model/__init__.py
adk_agui_middleware/data_model/context.py
adk_agui_middleware/data_model/error.py
adk_agui_middleware/data_model/log.py
adk_agui_middleware/data_model/session.py
adk_agui_middleware/event/__init__.py
adk_agui_middleware/event/error_event.py
adk_agui_middleware/handler/__init__.py
adk_agui_middleware/handler/agui_user.py
adk_agui_middleware/handler/session.py
adk_agui_middleware/handler/user_message.py
adk_agui_middleware/loggers/__init__.py
adk_agui_middleware/loggers/exception.py
adk_agui_middleware/loggers/logger.py
adk_agui_middleware/loggers/record_log.py
adk_agui_middleware/loggers/record_request_log.py
adk_agui_middleware/manager/__init__.py
adk_agui_middleware/manager/session.py
adk_agui_middleware/pattern/__init__.py
adk_agui_middleware/pattern/singleton.py
adk_agui_middleware/tools/__init__.py
adk_agui_middleware/tools/convert.py
adk_agui_middleware/tools/event_translator.py
adk_agui_middleware/tools/function_name.py
adk_agui_middleware/tools/json_encoder.py
adk_agui_middleware/tools/shutdown.py
adk_agui_py_middleware-0.1.3.dist-info/METADATA
adk_agui_py_middleware-0.1.3.dist-info/WHEEL
adk_agui_py_middleware-0.1.3.dist-info/licenses/LICENSE
adk_agui_py_middleware-0.1.3.dist-info/RECORD
