Metadata-Version: 2.4
Name: adk-agui-py-middleware
Version: 0.1.3
Summary: Python middleware bridging Google ADK agents with AGUI protocol via Server-Sent Events for real-time agent interactions
Project-URL: Homepage, https://github.com/DennySORA/adk-agui-py-middleware
Project-URL: Repository, https://github.com/DennySORA/adk-agui-py-middleware.git
Project-URL: Documentation, https://github.com/DennySORA/adk-agui-py-middleware#readme
Project-URL: Bug Tracker, https://github.com/DennySORA/adk-agui-py-middleware/issues
Author-email: DennySORA <dennysora.main@gmail.com>
Maintainer-email: DennySORA <dennysora.main@gmail.com>
License: MIT License
License-File: LICENSE
Keywords: agent,agui,fastapi,google-adk,middleware,sse
Classifier: Development Status :: 3 - Alpha
Classifier: Intended Audience :: Developers
Classifier: License :: OSI Approved :: MIT License
Classifier: Operating System :: OS Independent
Classifier: Programming Language :: Python :: 3
Classifier: Programming Language :: Python :: 3.13
Classifier: Topic :: Internet :: WWW/HTTP :: HTTP Servers
Classifier: Topic :: Scientific/Engineering :: Artificial Intelligence
Classifier: Topic :: Software Development :: Libraries :: Python Modules
Requires-Python: >=3.10
Requires-Dist: ag-ui-protocol>=0.1.8
Requires-Dist: fastapi>=0.104.0
Requires-Dist: google-adk>=1.9.0
Requires-Dist: pydantic-settings>=2.10.1
Requires-Dist: pydantic>=2.11.7
